ticketbudgeting/__init__.py
ticketbudgeting/ticketbudgeting.py
ticketbudgeting/htdocs/js/budgeting.js
ticketbudgeting/locale/messages.pot
ticketbudgeting/locale/de_DE/LC_MESSAGES/ticketbudgeting.po
TracBudgeting-0.6.8.dist-info/COPYING.txt
TracBudgeting-0.6.8.dist-info/METADATA
TracBudgeting-0.6.8.dist-info/WHEEL
TracBudgeting-0.6.8.dist-info/entry_points.txt
TracBudgeting-0.6.8.dist-info/top_level.txt
TracBudgeting-0.6.8.dist-info/RECORD
