Metadata-Version: 2.1
Name: TracBudgeting
Version: 0.6.8
Summary: Possibility to add budgeting information (estimation, cost, user) to tickets
Home-page: https://trac-hacks.org/wiki/BudgetingPlugin
Author: Gefasoft AG, Franz Mayer
Author-email: franz.mayer@gefasoft.de
License: 3-Clause BSD
Platform: UNKNOWN
Classifier: Framework :: Trac
Requires-Dist: Trac
